dialogx/__init__.py
dialogx/ctrlIcons.py
dialogx-1.1.dist-info/METADATA
dialogx-1.1.dist-info/WHEEL
dialogx-1.1.dist-info/top_level.txt
dialogx-1.1.dist-info/RECORD
