Metadata-Version: 2.1
Name: dialogx
Version: 1.1
Summary: A lightweight Python library for creating customizable and interactive dialogs and windows with Pygame.
Author: MySoft
Author-email: rixthetyrunt@gmail.com
Classifier: Programming Language :: Python :: 3
Classifier: License :: Other/Proprietary License
Classifier: Operating System :: Microsoft :: Windows
Requires-Dist: pygame
